README.md
pyproject.toml
imds/__init__.py
imds/__main__.py
imds/datasets.py
imds.egg-info/PKG-INFO
imds.egg-info/SOURCES.txt
imds.egg-info/dependency_links.txt
imds.egg-info/top_level.txt