Metadata-Version: 2.1
Name: imds
Version: 0.0.3
Summary: Download IMDb datasets
Author-email: ken <block24block@gmail.com>
Project-URL: Homepage, https://github.com/turnon/imds
Classifier: Programming Language :: Python :: 3
Classifier: License :: OSI Approved :: MIT License
Classifier: Operating System :: OS Independent
Requires-Python: >=3.8
